Metadata-Version: 1.2
Name: solution-efe-client-document
Version: 1.0.0
Summary: Paquete de client document
Home-page: UNKNOWN
Author: Rulman Ferro
Author-email: rulman26@gmail.com
License: MIT
Platform: UNKNOWN
Requires-Python: >=3.6
